send_tcp_in_one_datagram/__init__.py
send_tcp_in_one_datagram/send.py
send_tcp_in_one_datagram/lib/IP_Datagram.py
send_tcp_in_one_datagram/lib/TCP_Flags.py
send_tcp_in_one_datagram/lib/TCP_Segment.py
send_tcp_in_one_datagram/lib/__init__.py
send_tcp_in_one_datagram/lib/disable_auto_rst.py
send_tcp_in_one_datagram-0.0.4.dist-info/METADATA
send_tcp_in_one_datagram-0.0.4.dist-info/WHEEL
send_tcp_in_one_datagram-0.0.4.dist-info/RECORD
