Metadata-Version: 2.3
Name: send_tcp_in_one_datagram
Version: 0.0.4
Summary: Send a TCP payload in one IP datagram
Project-URL: Homepage, https://github.com/johnnyodonnell/python-send-tcp-in-one-datagram
Project-URL: Issues, https://github.com/johnnyodonnell/python-send-tcp-in-one-datagram/issues
Author-email: Johnny O'Donnell <odonnell_johnny@yahoo.com>
Classifier: License :: OSI Approved :: MIT License
Classifier: Operating System :: OS Independent
Classifier: Programming Language :: Python :: 3
Requires-Python: >=3.8
